mailru_im_command_bot/__init__.py
mailru_im_command_bot/command_bot.py
mailru_im_command_bot/types.py
mailru_im_command_bot-0.1.9.dist-info/LICENSE
mailru_im_command_bot-0.1.9.dist-info/WHEEL
mailru_im_command_bot-0.1.9.dist-info/METADATA
mailru_im_command_bot-0.1.9.dist-info/RECORD
