Metadata-Version: 2.1
Name: mailru-im-command-bot
Version: 0.1.9
Summary: Tiny lib for icq/myteam command bots
Home-page: https://github.com/dedefer/mailru-im-command-bot
License: MIT
Keywords: myteam,icq,bot,command
Author: Danila Fomin
Author-email: ddf1998@gmail.com
Requires-Python: >=3.7,<4.0
Classifier: License :: OSI Approved :: MIT License
Classifier: Programming Language :: Python :: 3
Classifier: Programming Language :: Python :: 3.7
Classifier: Programming Language :: Python :: 3.8
Classifier: Programming Language :: Python :: 3.9
Classifier: Topic :: Software Development :: Libraries :: Application Frameworks
Classifier: Topic :: Software Development :: Libraries :: Python Modules
Requires-Dist: mailru-im-bot (>=0.0.18)
Requires-Dist: mypy-extensions (>=0.4.3,<0.5.0)
Requires-Dist: typing-extensions (>=3.10.0,<4.0.0)
Project-URL: Repository, https://github.com/dedefer/mailru-im-command-bot
